practica_5_comparador/clk_divide.v
module clk_divide #(
    parameter FREQ = 50,
    parameter CLK_FREQ = 50_000_00
)(
    input clk, 
    input rst,
    output reg clk_div
   
);

reg [31:0] count;
localparam constantnum = CLK_FREQ / (2 * FREQ);
    always @(posedge clk or posedge rst) begin
        if (rst == 1)
         count <= 0;
        else if (count == constantnum -1)
            count <= 0;
        else count<= count +1;
    end

     always @(posedge clk or posedge rst) begin
        if (rst == 1)
         clk_div <= 0;
        else if (count == constantnum -1)
            clk_div <= ~clk_div;
        else clk_div <= clk_div;
    end



endmodule

Proyect_verilog/counter.v
module counter#(parameter pwm = 50,
    parameter CLK_FREQ = 5_000_000)(
	input clk,
	input rst,
	output reg [16:0] counter
	
);

clk_divide clock(.rst(rst),.clk(clk_divider));

always @(posedge clk or posedge rst) begin 
    if (rst)
        counter <= 0;
	else if 
			(counter == CLK_FREQ/pwm)
				counter <= 0;
			else 
				counter <= counter +1;
			
end

endmodule

practica_5_comparador/comparador.v
module comparador(
	input clk,
	input rst,
	input [7:0] in,
	output reg out
);

wire [16:0] count;
reg [16:0] comp;


counter countersin(.rst(rst),.clk(clk),.counter(count));

always @(posedge clk or posedge rst) begin 
	if (rst) begin
        
        comp <= 0;
        out  <= 0;
    end else begin
		comp = ((5000/180)*in) + 5000;
    if (count < comp)
	 	out <= 1;
	else
		out <= 0;
	end
	
end



endmodule

practica_5/pract5_w.v
module pract5_w (
    input  [1:0] KEY,
	 input MAX10_CLK1_50,
	 input  [7:0] SW,
    output [0:6] ARDUINO_IO,
    output [0:6] HEX0,
    output [0:6] HEX1,
    output [0:6] HEX2,
    output [0:6] HEX3
);


comparador wraper(.rst(KEY[0]),.clk(MAX10_CLK1_50),.in(SW[7:0]),.out(ARDUINO_IO[0]));

endmodule

practica_5_comparador/comparador_tb.v
module comparador_tb();

    reg MAX10_CLK1_50;
    reg [1:0] KEY;
    reg [7:0] SW;

    wire [6:0] ARDUINO_IO;
    wire [6:0] HEX0;
    wire [6:0] HEX1;
    wire [6:0] HEX2;
    wire [6:0] HEX3;
   

    pract5_w uut (
        .MAX10_CLK1_50(MAX10_CLK1_50),
        .KEY(KEY),
        .SW(SW),
        .ARDUINO_IO(ARDUINO_IO),
        .HEX0(HEX0),
        .HEX1(HEX1),
        .HEX2(HEX2),
        .HEX3(HEX3)
    );

    initial begin
        MAX10_CLK1_50 = 0;
        forever #10 MAX10_CLK1_50 = ~MAX10_CLK1_50;
    end

    initial begin
        KEY = 2'b11; 
        SW = 10'b0;

        #100;
        KEY[0] = 0; 
        #100;
        KEY[0] = 1; 
        #100;

        $display("Testing 0 degrees...");
        SW = 10'b0000000001;
        #2500; 

        // Test Case 2
        $display("Testing 90 degrees...");
        SW = 10'b0000000010;
        #2500;

        // Test Case 3
        $display("Testing 180 degrees...");
        SW = 10'b0000000100;
        #2500;
        
        $display("Test Complete");
        $stop;
    end

        initial begin
    $monitor("SW = %b",SW);
end

initial begin
    $dumpfile("comparador_tb.vcd");
    $dumpvars(0,comparador_tb);

end
      
endmodule

practica_5_comparador/comparador_tb.vcd
$date
	Mon Mar 02 08:05:41 2026
$end
$version
	Icarus Verilog
$end
$timescale
	1s
$end
$scope module comparador_tb $end
$var wire 7 ! HEX0 [6:0] $end
$var wire 7 " HEX1 [6:0] $end
$var wire 7 # HEX2 [6:0] $end
$var wire 7 $ HEX3 [6:0] $end
$var wire 7 % ARDUINO_IO [6:0] $end
$var reg 2 & KEY [1:0] $end
$var reg 1 ' MAX10_CLK1_50 $end
$var reg 8 ( SW [7:0] $end
$scope module uut $end
$var wire 7 ) HEX0 [0:6] $end
$var wire 7 * HEX1 [0:6] $end
$var wire 7 + HEX2 [0:6] $end
$var wire 7 , HEX3 [0:6] $end
$var wire 2 - KEY [1:0] $end
$var wire 1 ' MAX10_CLK1_50 $end
$var wire 8 . SW [7:0] $end
$var wire 7 / ARDUINO_IO [0:6] $end
$scope module wraper $end
$var wire 1 ' clk $end
$var wire 8 0 in [7:0] $end
$var wire 1 1 rst $end
$var wire 17 2 count [16:0] $end
$var reg 17 3 comp [16:0] $end
$var reg 1 4 out $end
$scope module countersin $end
$var wire 1 ' clk $end
$var wire 1 5 clk_divider $end
$var wire 1 1 rst $end
$var parameter 32 6 CLK_FREQ $end
$var parameter 32 7 pwm $end
$var reg 17 8 counter [16:0] $end
$scope module clock $end
$var wire 1 5 clk $end
$var wire 1 1 rst $end
$var parameter 32 9 CLK_FREQ $end
$var parameter 32 : FREQ $end
$var parameter 64 ; constantnum $end
$var reg 1 < clk_div $end
$var reg 32 = count [31:0] $end
$upscope $end
$upscope $end
$upscope $end
$upscope $end
$upscope $end
$enddefinitions $end
$comment Show the parameter values. $end
$dumpall
b1100001101010000 ;
b110010 :
b10011000100101101000000 9
b110010 7
b10011000100101101000000 6
$end
#0
$dumpvars
b0 =
0<
b0 8
z5
04
b0 3
b0 2
11
b0 0
b0zzzzzz /
b0 .
b11 -
bz ,
bz +
bz *
bz )
b0 (
0'
b11 &
b0zzzzzz %
bz $
bz #
bz "
bz !
$end
#10
1'
#20
0'
#30
1'
#40
0'
#50
1'
#60
0'
#70
1'
#80
0'
#90
1'
#100
01
0'
b10 &
b10 -
#110
b1 2
b1 8
b1zzzzzz %
b1zzzzzz /
14
b1001110001000 3
1'
#120
0'
#130
b10 2
b10 8
1'
#140
0'
#150
b11 2
b11 8
1'
#160
0'
#170
b100 2
b100 8
1'
#180
0'
#190
b101 2
b101 8
1'
#200
b0zzzzzz %
b0zzzzzz /
04
b0 3
b0 2
b0 8
11
0'
b11 &
b11 -
#210
1'
#220
0'
#230
1'
#240
0'
#250
1'
#260
0'
#270
1'
#280
0'
#290
1'
#300
0'
b1 (
b1 .
b1 0
