Practica_1_prime_numbers/num_primos.v
module num_primos(
input [3:0] N,
output reg out
);


always @(*)
begin
    case(N)
    2: out = 1;
    3: out = 1;
    5: out = 1;
    7: out = 1;
    11: out = 1;
    13: out = 1;
    default: out = 0;


    endcase
    end
endmodule

Practica_1_prime_numbers/num_primos_tb.v
module num_primos_tb();
reg [3:0] N;
wire out;
integer i ;

num_primos DUT(.N(N),.out(out));


initial begin
    $display("inicia sim");
    
    N = 0;
    for (i = 0; i < 16; i = i + 1) begin
    N = i[3:0];   
    #10;

    end 
   
    
    $display("fin");
    $stop;
    $finish;

end

initial begin
    $monitor("N = %b,out = %b",N,out);

end

initial begin
    $dumpfile("num_primos_tb.vcd");
    $dumpvars(0,num_primos_tb);

end


endmodule

Practices/Practice_1_prime_numbers/num_primos_tb.vcd
$date
	Fri Feb 13 08:48:11 2026
$end
$version
	Icarus Verilog
$end
$timescale
	1s
$end
$scope module num_primos_tb $end
$var wire 1 ! out $end
$var reg 4 " N [3:0] $end
$var integer 32 # i [31:0] $end
$scope module DUT $end
$var wire 4 $ N [3:0] $end
$var reg 1 ! out $end
$upscope $end
$upscope $end
$enddefinitions $end
$comment Show the parameter values. $end
$dumpall
$end
#0
$dumpvars
b0 $
b0 #
b0 "
0!
$end
#10
b1 "
b1 $
b1 #
#20
1!
b10 "
b10 $
b10 #
#30
b11 "
b11 $
b11 #
#40
0!
b100 "
b100 $
b100 #
#50
1!
b101 "
b101 $
b101 #
#60
0!
b110 "
b110 $
b110 #
#70
1!
b111 "
b111 $
b111 #
#80
0!
b1000 "
b1000 $
b1000 #
#90
b1001 "
b1001 $
b1001 #
#100
b1010 "
b1010 $
b1010 #
#110
1!
b1011 "
b1011 $
b1011 #
#120
0!
b1100 "
b1100 $
b1100 #
#130
1!
b1101 "
b1101 $
b1101 #
#140
0!
b1110 "
b1110 $
b1110 #
#150
b1111 "
b1111 $
b1111 #
