Mini_challenges/mini_challenge_1/mini_challenge.v
module mini_challenge #(
    parameter integer N = 4  //define el numero de bits de 1 o 2^N de iteraciones 
)(
    input  clk,
    input  rst,
    input  in,
    output reg  out
);

reg [N-1:0] cnt;    //genero el count para que solo cambie hasta que haga todas las iteraciones

always @(posedge clk) begin
    if (rst) begin  //inicio las variables en 0 cuando el rst cambia 
        out <= 0;
        cnt <= 0;
    end else begin
    if (in == out) begin  // verifica que la entrada no tenga cambios
        cnt <= 0;
    end else begin        // como si es difernte el in y el out
        if (cnt == {N{1'b1}}) begin // Si el counter cumple con 2^N veces 1 es decir N = 4 = b'1111
            out <= in;              // Si se cumple por ese tiempo entonces el output cambia y reinicamos el counter
            cnt <= 0;
        end else begin
            cnt <= cnt + 1'b1;     // Se suma 1 bit al counter 
        end
    end
end
end

endmodule

Mini_challenge/mini_challenge_tb.v
module mini_challenge_tb();
    reg  clk,  rst,  in;
    wire  out;

    mini_challenge DUT(.rst(rst),.in(in),.out(out),.clk(clk));

      initial begin
        clk= 0;

    forever 
    #10 clk =~clk;
    end

    initial begin
    
    $display("sim iniciada") ; 
	   rst = 1;
       in  = 0;
		#20;
		rst = 0;   
	 
    repeat(50)
    begin
        in = $random%2;					 // SE GENERA UN NUMERO RANDOM de 1 bit 0-1
		   repeat(40) @(posedge clk);  // Se hacen 40 posedge del clk 
    end


    
    $display("sim finalizada"); 
    $stop;
    $finish;
    end
  


initial begin
    $monitor("clk = %b ,in= %b ,out = %b", clk,in,out);
end

initial begin
    $dumpfile("mini_challenge_tb.vcd");
    $dumpvars(0,mini_challenge_tb);

end
	 
endmodule

Mini_challenge/mini_challenge_tb.vcd
$date
	Mon Mar 02 20:01:52 2026
$end
$version
	Icarus Verilog
$end
$timescale
	1s
$end
$scope module mini_challenge_tb $end
$var wire 1 ! out $end
$var reg 1 " clk $end
$var reg 1 # in $end
$var reg 1 $ rst $end
$scope module DUT $end
$var wire 1 " clk $end
$var wire 1 # in $end
$var wire 1 $ rst $end
$var parameter 32 % N $end
$var reg 4 & cnt [3:0] $end
$var reg 1 ! out $end
$upscope $end
$upscope $end
$enddefinitions $end
$comment Show the parameter values. $end
$dumpall
b100 %
$end
#0
$dumpvars
bx &
1$
0#
0"
x!
$end
#10
b0 &
0!
1"
#20
0"
0$
#30
1"
#40
0"
#50
1"
#60
0"
#70
1"
#80
0"
#90
1"
#100
0"
#110
1"
#120
0"
#130
1"
#140
0"
#150
1"
#160
0"
#170
1"
#180
0"
#190
1"
#200
0"
#210
1"
#220
0"
#230
1"
#240
0"
#250
1"
#260
0"
#270
1"
#280
0"
#290
1"
#300
0"
#310
1"
#320
0"
#330
1"
#340
0"
#350
1"
#360
0"
#370
1"
#380
0"
#390
1"
#400
0"
#410
1"
#420
0"
#430
1"
#440
0"
#450
1"
#460
0"
#470
1"
#480
0"
#490
1"
#500
0"
#510
1"
#520
0"
#530
1"
#540
0"
#550
1"
#560
0"
#570
1"
#580
0"
#590
1"
#600
0"
#610
1"
#620
0"
#630
1"
#640
0"
#650
1"
#660
0"
#670
1"
#680
0"
#690
1"
#700
0"
#710
1"
#720
0"
#730
1"
#740
0"
#750
1"
#760
0"
#770
1"
#780
0"
#790
1"
#800
0"
#810
1#
1"
#820
0"
#830
b1 &
1"
#840
0"
#850
b10 &
1"
#860
0"
#870
b11 &
1"
#880
0"
#890
b100 &
1"
#900
0"
#910
b101 &
1"
#920
0"
#930
b110 &
1"
#940
0"
#950
b111 &
1"
#960
0"
#970
b1000 &
1"
#980
0"
#990
b1001 &
1"
#1000
0"
#1010
b1010 &
1"
#1020
0"
#1030
b1011 &
1"
#1040
0"
#1050
b1100 &
1"
#1060
0"
#1070
b1101 &
1"
#1080
0"
#1090
b1110 &
1"
#1100
0"
#1110
b1111 &
1"
#1120
0"
#1130
b0 &
1!
1"
